pgex/__init__.py
pgex/gaming/__init__.py
pgex/gaming/animated_sprite.py
pgex/gaming/animation.py
pgex/gaming/base_sprite.py
pgex/gaming/simple_sprite.py
pgex/parameters/__init__.py
pgex/parameters/colors.py
pgex/widgets/__init__.py
pgex/widgets/button.py
pgex/widgets/entry.py
pgex/widgets/text.py
pgex-0.4.4.dist-info/LICENSE
pgex-0.4.4.dist-info/METADATA
pgex-0.4.4.dist-info/WHEEL
pgex-0.4.4.dist-info/top_level.txt
pgex-0.4.4.dist-info/RECORD
