Metadata-Version: 2.1
Name: pgex
Version: 0.4.4
Summary: A Python PyGame package extension
Home-page: https://github.com/IvanFoke/pgex
Author: Ivan Foke
Author-email: ivan.foke@gmail.com
License: UNKNOWN
Platform: UNKNOWN
Classifier: Programming Language :: Python :: 3
Classifier: License :: OSI Approved :: MIT License
Classifier: Operating System :: OS Independent
Requires-Python: >=3.6
